test2ref-1.1.1.dist-info/METADATA
test2ref-1.1.1.dist-info/WHEEL
test2ref-1.1.1.dist-info/entry_points.txt
test2ref-1.1.1.dist-info/licenses/LICENSE
test2ref/__init__.py
test2ref-1.1.1.dist-info/RECORD
