Metadata-Version: 2.1
Name: test2ref
Version: 1.1.1
Summary: Testing Against Learned Reference Data
Classifier: Programming Language :: Python :: 3
Classifier: Operating System :: OS Independent
Project-URL: Homepage, https://github.com/nbiotcloud/test2ref
Project-URL: Documentation, https://test2ref.readthedocs.io/en/stable/
Project-URL: Bug Tracker, https://github.com/nbiotcloud/test2ref/issues
Requires-Python: <4.0,>=3.10.0
Requires-Dist: binaryornot>=0.4.4
